{
  "id": "tsutatsu-hojin-790704-01",
  "title": "金融機関の保有する譲渡性預金の経理について",
  "category": "hojin",
  "canonical_url": "https://www.nta.go.jp/law/tsutatsu/kobetsu/hojin/790704/01.htm",
  "source_type": "tsutatsu",
  "crawled_at": "2026-04-12T10:42:51.598Z",
  "updated_at": null,
  "published_at": null,
  "content_hash": "sha256:3bf3901715ce8491e4a30be6034dad66684bac9eea7259d32acba5e14203c16d",
  "license": "public_data",
  "version": 1,
  "aliases": [
    "金融機関の保有する譲渡性預金の経理について"
  ],
  "headings": [
    "金融機関の保有する譲渡性預金の経理について",
    "金融機関の保有する譲渡性預金の経理について",
    "金融機関の保有する譲渡性預金の経理について（昭和54.6.14付昭54調々第49号照会に対する回答）",
    "金融機関の保有する譲渡性預金の経理について"
  ],
  "citation": null,
  "document_number": null,
  "tags": [
    "法人税"
  ],
  "etag": "\"159f-60f34fee90118\"",
  "last_modified": "Thu, 18 Jan 2024 09:29:09 GMT"
}
