{
  "id": "4557",
  "title": "親名義の建物に子供が増築したとき",
  "category": "zoyo",
  "category_path": "贈与税、所得税",
  "canonical_url": "https://www.nta.go.jp/taxes/shiraberu/taxanswer/zoyo/4557.htm",
  "source_type": "tax_answer",
  "crawled_at": "2026-04-12T08:15:37.223Z",
  "updated_at": null,
  "published_at": null,
  "content_hash": "sha256:a840fe4f55a73df60ede4eda1f3535086703fb98b5fe768eecc16797afaf841e",
  "license": "public_data",
  "version": 1,
  "aliases": [
    "No.4557 親名義の建物に子供が増築したとき",
    "4557 親名義の建物に子供が増築したとき"
  ],
  "headings": [
    "親名義の建物に子供が増築したとき",
    "対象税目",
    "概要",
    "贈与税の課税",
    "所得税の課税",
    "根拠法令等",
    "関連リンク",
    "お問い合わせ先"
  ],
  "etag": "\"33c3-63fec71bbc9e0\"",
  "last_modified": "Mon, 29 Sep 2025 08:30:13 GMT"
}
