{
  "id": "tsutatsu-chosyu-05-03-05-118-01",
  "title": "第118条関係　売却決定通知書の交付",
  "category": "chosyu",
  "canonical_url": "https://www.nta.go.jp/law/tsutatsu/kihon/chosyu/05/03/05/118/01.htm",
  "source_type": "tsutatsu",
  "crawled_at": "2026-04-12T10:01:41.384Z",
  "updated_at": null,
  "published_at": null,
  "content_hash": "sha256:a90be8411b701103d24384aa7ec7445e3f1077ced9f33db6a8a9dc038b047385",
  "license": "public_data",
  "version": 1,
  "aliases": [
    "第118条関係　売却決定通知書の交付"
  ],
  "headings": [
    "第118条関係　売却決定通知書の交付",
    "第118条関係　売却決定通知書の交付",
    "売却決定通知書",
    "交付しない場合"
  ],
  "citation": null,
  "document_number": null,
  "tags": [
    "chosyu"
  ],
  "etag": "\"10bc-60f350892e580\"",
  "last_modified": "Thu, 18 Jan 2024 09:31:51 GMT"
}
