{
  "id": "saiketsu-06-118",
  "title": "(平成26年10月28日裁決)",
  "category": "附帯税",
  "category_code": "06",
  "canonical_url": "https://www.kfs.go.jp/service/JP/97/03/index.html",
  "source_type": "saiketsu",
  "crawled_at": "2026-04-12T06:30:00.000Z",
  "updated_at": null,
  "published_at": "2014-10-28",
  "content_hash": "sha256:a345bf58647f3282c889c1b175ad193ff25a49ac744518b3db6e778e0d5dcf70",
  "license": "国税不服審判所 公表裁決事例（利用規約に従って再配布）",
  "version": 1,
  "aliases": [
    "(平成26年10月28日裁決)",
    "97-03",
    "平成26年10月28日裁決"
  ],
  "headings": [
    "(平成26年10月28日裁決)",
    "1　事実",
    "(1)　事案の概要",
    "(2)　審査請求に至る経緯",
    "(3)　関係法令等の要旨",
    "(4)　基礎事実",
    "(5)　争点",
    "2　主張",
    "(1)　争点イについて",
    "(2)　争点ロについて",
    "3　判断",
    "(1)　争点イについて",
    "(2)　争点ロについて",
    "(3)　本件法人税賦課決定処分について",
    "(4)　本件消費税等賦課決定処分について",
    "(5)　その他"
  ],
  "citation": "平成26年10月28日裁決",
  "document_number": "97-03",
  "tags": [
    "附帯税",
    "所得税",
    "法人税",
    "消費税"
  ],
  "etag": "\"78ef-64e39889afce8\"",
  "last_modified": "Mon, 30 Mar 2026 08:21:12 GMT"
}
