{
  "id": "4155",
  "title": "相続税の税率",
  "category": "sozoku",
  "category_path": "相続税",
  "canonical_url": "https://www.nta.go.jp/taxes/shiraberu/taxanswer/sozoku/4155.htm",
  "source_type": "tax_answer",
  "crawled_at": "2026-04-12T08:14:41.113Z",
  "updated_at": null,
  "published_at": null,
  "content_hash": "sha256:fe9af44ea6544e4672f686e05f731667242aa8632c1246678a33879073f49639",
  "license": "public_data",
  "version": 1,
  "aliases": [
    "No.4155 相続税の税率",
    "4155 相続税の税率"
  ],
  "headings": [
    "相続税の税率",
    "対象税目",
    "概要",
    "相続税の税率",
    "根拠法令等",
    "関連リンク",
    "関連コード",
    "お問い合わせ先"
  ],
  "etag": "\"7c30-641b4d62ccd38\"",
  "last_modified": "Wed, 22 Oct 2025 01:00:03 GMT"
}
