{
  "id": "qa-joto-14-25",
  "title": "買取りの申出を受けた者から収用対象資産を相続により取得した者の「買取りの申出のあった日」",
  "category": "joto",
  "category_path": "譲渡所得",
  "canonical_url": "https://www.nta.go.jp/law/shitsugi/joto/14/25.htm",
  "source_type": "qa_case",
  "crawled_at": "2026-04-12T05:51:44.395Z",
  "updated_at": null,
  "published_at": null,
  "content_hash": "sha256:3cf14214403b67376fcf2c74f407ef0ac16544b0b056610f3500a0f2e570a762",
  "license": "国税庁 質疑応答事例（CC-BY 4.0 互換）",
  "version": 1,
  "aliases": [
    "買取りの申出を受けた者から収用対象資産を相続により取得した者の「買取りの申出のあった日」",
    "14-25"
  ],
  "headings": [
    "買取りの申出を受けた者から収用対象資産を相続により取得した者の「買取りの申出のあった日」",
    "買取りの申出を受けた者から収用対象資産を相続により取得した者の「買取りの申出のあった日」",
    "【照会要旨】",
    "【回答要旨】",
    "【関係法令通達】"
  ],
  "citation": "租税特別措置法第33条の4第3項",
  "document_number": "14-25",
  "tags": [
    "譲渡所得"
  ],
  "etag": "\"15b9-6450805900f30\"",
  "last_modified": "Wed, 03 Dec 2025 08:30:15 GMT"
}
