{
  "id": "tsutatsu-igi-02_02-02_02_02",
  "title": "第18条 《審査請求期間》関係",
  "category": "igi",
  "canonical_url": "https://www.nta.go.jp/law/tsutatsu/kihon/igi/02_02/02_02_02.htm",
  "source_type": "tsutatsu",
  "crawled_at": "2026-04-12T06:01:53.985Z",
  "updated_at": null,
  "published_at": null,
  "content_hash": "sha256:8d5dc6a6d6aa44bf6a8b1d74233552df96b4ded935daa614fb1559adeb45643e",
  "license": "public_data",
  "version": 1,
  "aliases": [
    "第18条 《審査請求期間》関係",
    "第2節 審査請求の手続"
  ],
  "headings": [
    "第18条 《審査請求期間》関係",
    "第18条 《審査請求期間》関係",
    "（正当な理由）",
    "（第1項と第2項との適用関係）",
    "（災害等による期限の延長との関係）",
    "（処分があった日）",
    "（期間の計算）",
    "（審査請求書が郵便又は信書便で提出された場合）",
    "第19条 《審査請求書の提出》関係",
    "（口頭による不服申立て）",
    "（審査請求書の記載事項等）",
    "第20条 《口頭による審査請求》関係",
    "（国税関係処分等についての不適用）",
    "第22条 《誤った教示をした場合の救済》関係",
    "（適用範囲）",
    "（教示）",
    "（審査請求とみなされた場合の副本）",
    "第23条 《審査請求書の補正》関係",
    "（補正命令を行う場合）",
    "（補正命令等）",
    "第26条 《執行停止の取消し》関係",
    "（その他事情が変更したとき）",
    "第27条 《審査請求の取下げ》関係",
    "（取下げの権限等）"
  ],
  "citation": "第2節 審査請求の手続",
  "document_number": null,
  "tags": [
    "不服申立"
  ],
  "etag": "\"20ac-60f3505d55bc0\"",
  "last_modified": "Thu, 18 Jan 2024 09:31:05 GMT"
}
