{
  "id": "tsutatsu-kihatsu-kihatu04-08",
  "title": "第8節　特定用途免税",
  "category": "kihatsu",
  "canonical_url": "https://www.nta.go.jp/law/tsutatsu/kihon/kihatsu/kihatu04/08.htm",
  "source_type": "tsutatsu",
  "crawled_at": "2026-04-12T10:42:53.516Z",
  "updated_at": null,
  "published_at": null,
  "content_hash": "sha256:806ab16e1dd316b41aac9bf6576b0bfa00fda3b8e1f31c0f9818e2832e6d5ea9",
  "license": "public_data",
  "version": 1,
  "aliases": [
    "第8節　特定用途免税"
  ],
  "headings": [
    "第8節　特定用途免税",
    "第8節　特定用途免税",
    "（特定用途の範囲等）",
    "（免税規格の測定等）",
    "（製造場における特定用途免税）",
    "（小口容器詰めみなし揮発油の特定用途免税の特例）",
    "（試験成績書）",
    "（移出に係る揮発油の特定用途免税手続の特例）"
  ],
  "citation": null,
  "document_number": null,
  "tags": [
    "kihatsu"
  ],
  "etag": "\"3d2c-60f3505785b28\"",
  "last_modified": "Thu, 18 Jan 2024 09:30:59 GMT"
}
