{
  "id": "qa-sozoku-06-03",
  "title": "相続税法第15条第3項の規定により実子とみなされる養子の範囲",
  "category": "sozoku",
  "category_path": "相続税・贈与税",
  "canonical_url": "https://www.nta.go.jp/law/shitsugi/sozoku/06/03.htm",
  "source_type": "qa_case",
  "crawled_at": "2026-04-12T05:52:20.017Z",
  "updated_at": null,
  "published_at": null,
  "content_hash": "sha256:d1c21f3c6de774ca20704d05970a602968edd6cbef2b0406d652ad29f0c46664",
  "license": "国税庁 質疑応答事例（CC-BY 4.0 互換）",
  "version": 1,
  "aliases": [
    "相続税法第15条第3項の規定により実子とみなされる養子の範囲",
    "06-03"
  ],
  "headings": [
    "相続税法第15条第3項の規定により実子とみなされる養子の範囲",
    "相続税法第15条第3項の規定により実子とみなされる養子の範囲",
    "【照会要旨】",
    "【回答要旨】",
    "【関係法令通達】"
  ],
  "citation": "相続税法第15条第2項、第3項\n民法第887条第2項",
  "document_number": "06-03",
  "tags": [
    "相続税・贈与税"
  ],
  "etag": "\"161b-6450805323f90\"",
  "last_modified": "Wed, 03 Dec 2025 08:30:09 GMT"
}
