{
  "id": "2674",
  "title": "中途就職者の年末調整",
  "category": "gensen",
  "category_path": "源泉所得税",
  "canonical_url": "https://www.nta.go.jp/taxes/shiraberu/taxanswer/gensen/2674.htm",
  "source_type": "tax_answer",
  "crawled_at": "2026-04-12T06:03:56.777Z",
  "updated_at": null,
  "published_at": null,
  "content_hash": "sha256:9a91b5898b8856fd068353fc7760b3186367e380ad4f54c061059068c3b133c8",
  "license": "public_data",
  "version": 1,
  "aliases": [
    "No.2674 中途就職者の年末調整",
    "2674 中途就職者の年末調整"
  ],
  "headings": [
    "中途就職者の年末調整",
    "対象税目",
    "概要",
    "手続き",
    "根拠法令等",
    "関連リンク",
    "関連コード",
    "お問い合わせ先"
  ],
  "etag": "\"387c-6418ff4cf7f80\"",
  "last_modified": "Mon, 20 Oct 2025 05:00:03 GMT"
}
