{
  "id": "tsutatsu-hojin-07-07_04_03",
  "title": "第3款　増加償却",
  "category": "hojin",
  "canonical_url": "https://www.nta.go.jp/law/tsutatsu/kihon/hojin/07/07_04_03.htm",
  "source_type": "tsutatsu",
  "crawled_at": "2026-04-12T02:29:33.600Z",
  "updated_at": null,
  "published_at": null,
  "content_hash": "sha256:91ab654c281cf22cf6a827dd5708c45ffcbd18b62d29cab80ba93c301c97f691",
  "license": "public_data",
  "version": 1,
  "aliases": [
    "第3款　増加償却"
  ],
  "headings": [
    "第3款　増加償却",
    "第3款　増加償却",
    "(増加償却の適用単位)",
    "(中間期間で増加償却を行った場合)",
    "(貸与を受けている機械及び装置がある場合の増加償却)"
  ],
  "citation": null,
  "document_number": null,
  "tags": [
    "法人税"
  ],
  "etag": "\"12e1-60f35083b47d0\"",
  "last_modified": "Thu, 18 Jan 2024 09:31:46 GMT"
}
