{
  "id": "tsutatsu-renketsu-02-02_01_03_01",
  "title": "第4款　短期売買商品等の譲渡に係る損益",
  "category": "renketsu",
  "canonical_url": "https://www.nta.go.jp/law/tsutatsu/kihon/renketsu/02/02_01_03_01.htm",
  "source_type": "tsutatsu",
  "crawled_at": "2026-04-12T10:42:54.096Z",
  "updated_at": null,
  "published_at": null,
  "content_hash": "sha256:d7def57e16b475285889289ab0971df9b410758222845d9de8f2c0ab23a45c12",
  "license": "public_data",
  "version": 1,
  "aliases": [
    "第4款　短期売買商品等の譲渡に係る損益"
  ],
  "headings": [
    "第4款　短期売買商品等の譲渡に係る損益",
    "第4款　短期売買商品等の譲渡に係る損益",
    "（短期売買商品等の譲渡に係る損益の計上時期の特例）",
    "（短期売買業務の廃止に伴う短期売買商品等から短期売買商品等以外の資産への変更）",
    "（暗号資産信用取引に係る現渡しの方法による決済を行った場合の損益の計上時期）"
  ],
  "citation": null,
  "document_number": null,
  "tags": [
    "renketsu"
  ],
  "etag": "\"1796-60f35056a0b18\"",
  "last_modified": "Thu, 18 Jan 2024 09:30:58 GMT"
}
