{
  "id": "tsutatsu-shotoku-shinkoku-780301-01",
  "title": "個人立幼稚園の所得税法上の税務処理について",
  "category": "shotoku",
  "canonical_url": "https://www.nta.go.jp/law/tsutatsu/kobetsu/shotoku/shinkoku/780301/01.htm",
  "source_type": "tsutatsu",
  "crawled_at": "2026-04-12T10:43:03.580Z",
  "updated_at": null,
  "published_at": null,
  "content_hash": "sha256:0710a7f79c21958685098b8bc002c1ca506810750cafb7c1781c5da6f6a535ed",
  "license": "public_data",
  "version": 1,
  "aliases": [
    "個人立幼稚園の所得税法上の税務処理について"
  ],
  "headings": [
    "個人立幼稚園の所得税法上の税務処理について",
    "個人立幼稚園の所得税法上の税務処理について",
    "個人立幼稚園の所得税法上の税務処理について\n（昭和53年2月24日付照会に対する回答）",
    "個人立幼稚園の税制について"
  ],
  "citation": null,
  "document_number": null,
  "tags": [
    "所得税"
  ],
  "etag": "\"1b7b-60f34f0d86b18\"",
  "last_modified": "Thu, 18 Jan 2024 09:25:13 GMT"
}
