{
  "id": "bunshokaito-shotoku-981202-01",
  "title": "損害保険代理店の役員・使用人が証券取引法第65条の2第11項に規定する特定証券業務を行った場合に支払われる対価の税務上の取扱い",
  "category": "shotoku",
  "canonical_url": "https://www.nta.go.jp/law/bunshokaito/shotoku/981202/01.htm",
  "source_type": "written_answer",
  "crawled_at": "2026-04-12T06:46:38.321Z",
  "updated_at": null,
  "published_at": null,
  "content_hash": "sha256:450cc99e1e20d7458b8316f66ba9150ef51ecc4e28b0fa351f06db8b408a00a5",
  "license": "国税庁 文書回答事例（利用規約に従って再配布）",
  "version": 1,
  "aliases": [],
  "headings": [
    "損害保険代理店の役員・使用人が証券取引法第65条の2第11項に規定する特定証券業務を行った場合に支払われる対価の税務上の取扱い",
    "損害保険代理店の役員・使用人が証券取引法第65条の2第11項に規定する特定証券業務を行った場合に支払われる対価の税務上の取扱い （平成10年11月30日付経財第98－156号照会に対する回答）",
    "1　業務委託契約の概要",
    "2　税務上の取扱い"
  ],
  "citation": "標題のことについては、(社)日本損害保険協会から別紙 2 のとおり照会があり、これに対して当庁課税部長名をもって別紙1のとおり回答したから、了知されたい。",
  "document_number": "981202-01",
  "page_offsets": [],
  "etag": "\"1e9c-64df9e9f8efa8\"",
  "last_modified": "Fri, 27 Mar 2026 04:27:07 GMT"
}
