{
  "id": "tsutatsu-shotoku-01-05",
  "title": "〔繰延資産（第20号関係）〕",
  "category": "shotoku",
  "canonical_url": "https://www.nta.go.jp/law/tsutatsu/kihon/shotoku/01/05.htm",
  "source_type": "tsutatsu",
  "crawled_at": "2026-04-12T02:33:34.404Z",
  "updated_at": null,
  "published_at": null,
  "content_hash": "sha256:1f2a3ed4545ac90b62e7fbf6500964f147ede058190c066e840187ff113e98be",
  "license": "public_data",
  "version": 1,
  "aliases": [
    "繰延資産（第20号関係）"
  ],
  "headings": [
    "〔繰延資産（第20号関係）〕",
    "〔繰延資産（第20号関係）〕",
    "（公共的施設の設置又は改良のために支出する費用）",
    "（共同的施設の設置又は改良のために支出する費用）",
    "（簡易な施設の負担金の必要経費算入）",
    "（資産を賃借するための権利金等）",
    "（ノーハウの頭金等）",
    "（広告宣伝の用に供する資産を贈与したことにより生ずる費用）",
    "（スキー場のゲレンデ整備費用）",
    "（出版権の設定の対価）",
    "（同業者団体等の加入金）",
    "（職業運動選手等の契約金等）"
  ],
  "citation": null,
  "document_number": null,
  "tags": [
    "所得税"
  ],
  "etag": "\"2b1b-6446716472328\"",
  "last_modified": "Tue, 25 Nov 2025 08:30:06 GMT"
}
