{
  "id": "tsutatsu-tainoshobun-03-02-36_02",
  "title": "第36条の2関係 航空機等に対する滞納処分",
  "category": "tainoshobun",
  "canonical_url": "https://www.nta.go.jp/law/tsutatsu/kihon/tainoshobun/03/02/36_02.htm",
  "source_type": "tsutatsu",
  "crawled_at": "2026-04-12T10:43:08.572Z",
  "updated_at": null,
  "published_at": null,
  "content_hash": "sha256:5be5174244d6f8b58ebfaf32d5f374366fe93165ffcc10ee379c08419540fc79",
  "license": "public_data",
  "version": 1,
  "aliases": [
    "第36条の2関係 航空機等に対する滞納処分"
  ],
  "headings": [
    "第36条の2関係 航空機等に対する滞納処分",
    "第36条の2関係 航空機等に対する滞納処分",
    "1　強制執行又は競売が開始されている航空機に対する滞納処分",
    "2　仮差押えの執行がされている航空機に対する滞納処分",
    "3　強制執行又は競売が開始されている自助車等に対する滞納処分",
    "4　仮差押えの執行がされている自動車等に対する滞納処分"
  ],
  "citation": null,
  "document_number": null,
  "tags": [
    "tainoshobun"
  ],
  "etag": "\"2b18-60f35017b92d8\"",
  "last_modified": "Thu, 18 Jan 2024 09:29:52 GMT"
}
