{
  "id": "tsutatsu-kansetsu-160425-index",
  "title": "消費税の軽減税率制度に関する申告書等の様式の制定について(法令解釈通達)",
  "category": "kansetsu",
  "canonical_url": "https://www.nta.go.jp/law/tsutatsu/kobetsu/kansetsu/160425/index.htm",
  "source_type": "tsutatsu",
  "crawled_at": "2026-04-12T10:43:13.667Z",
  "updated_at": null,
  "published_at": null,
  "content_hash": "sha256:aed9f03552b369e5f8658c26f1482b241ef5e26c7c80e5d18f4bd9baf3534710",
  "license": "public_data",
  "version": 1,
  "aliases": [
    "消費税の軽減税率制度に関する申告書等の様式の制定について(法令解釈通達)"
  ],
  "headings": [
    "消費税の軽減税率制度に関する申告書等の様式の制定について(法令解釈通達)",
    "消費税の軽減税率制度に関する申告書等の様式の制定について(法令解釈通達)"
  ],
  "citation": null,
  "document_number": null,
  "tags": [
    "kansetsu",
    "消費税"
  ],
  "etag": "\"38a6-64dfaca74a608\"",
  "last_modified": "Fri, 27 Mar 2026 05:29:54 GMT"
}
