{
  "id": "tsutatsu-inshi-betsu01-04",
  "title": "第3号文書",
  "category": "inshi",
  "canonical_url": "https://www.nta.go.jp/law/tsutatsu/kihon/inshi/betsu01/04.htm",
  "source_type": "tsutatsu",
  "crawled_at": "2026-04-12T10:42:52.469Z",
  "updated_at": null,
  "published_at": null,
  "content_hash": "sha256:30583ab4d838225a18d9ad0bb72026042378950ee3f91ea801476435abefdf04",
  "license": "public_data",
  "version": 1,
  "aliases": [
    "第3号文書",
    "1"
  ],
  "headings": [
    "第3号文書",
    "第3号文書",
    "（約束手形又は為替手形の意義）",
    "（振出人の署名を欠く白地手形の作成者）",
    "（白地手形の作成の時期）",
    "（手形金額の記載のない手形）",
    "（一覧払の手形の意義）",
    "（満期の記載がないかどうかの判定）",
    "（参着払手形）",
    "（手形法第34条第2項の定めをするものの意義）",
    "（金融機関を振出人及び受取人とする手形の意義）",
    "（銀行の意義）",
    "（貯金又は定期積金の受入れを行うものの意義）",
    "（外国通貨により手形金額が表示される手形についての非課税規定の適用）",
    "（外国為替手形の複本）",
    "（銀行等の意義）",
    "（税率が軽減される居住者振出しの手形の範囲）",
    "（税率が軽減される手形の担保となる外国の銀行が振り出す手形の範囲）",
    "（税率が軽減される銀行等振出しの手形の範囲）",
    "第4号文書",
    "（法人の社員又は出資者の意義）",
    "（特別の法律により法人の発行する債券の範囲）",
    "（投資信託の受益証券、貸付信託の受益証券、特定目的信託の受益証券及び受益証券発行信託の受益証券の意義）",
    "（社債券の範囲）",
    "（基金証券の意義）",
    "（合併存続会社等が訂正して発行する株券）",
    "（譲渡制限の旨を記載する株券）",
    "（払込金額の意義）",
    "（払込金額がない場合の意義）",
    "（資本金の額及び資本準備金の額の合計額の意義）",
    "（出資総額の意義）"
  ],
  "citation": null,
  "document_number": "1",
  "tags": [
    "inshi"
  ],
  "etag": "\"4250-60f3505c9c300\"",
  "last_modified": "Thu, 18 Jan 2024 09:31:05 GMT"
}
