{
  "id": "7140",
  "title": "印紙税額の一覧表（その1）第1号文書から第4号文書まで",
  "category": "inshi",
  "category_path": "印紙税",
  "canonical_url": "https://www.nta.go.jp/taxes/shiraberu/taxanswer/inshi/7140.htm",
  "source_type": "tax_answer",
  "crawled_at": "2026-04-12T07:57:50.663Z",
  "updated_at": null,
  "published_at": null,
  "content_hash": "sha256:f1fbfe85e52497913cbed9460b217e2d68f3ea4b706e8b8df5b0f58221688105",
  "license": "public_data",
  "version": 1,
  "aliases": [
    "No.7140 印紙税額の一覧表（その1）第1号文書から第4号文書まで",
    "7140 印紙税額の一覧表（その1）第1号文書から第4号文書まで"
  ],
  "headings": [
    "印紙税額の一覧表（その1）第1号文書から第4号文書まで",
    "対象税目",
    "概要",
    "第1号文書から第4号文書までの印紙税額の一覧表",
    "災害に関する措置",
    "関連リンク",
    "関連コード",
    "お問い合わせ先"
  ],
  "etag": "\"8aa4-64dfb2495e020\"",
  "last_modified": "Fri, 27 Mar 2026 05:55:06 GMT"
}
