{
  "id": "tsutatsu-shohi-17-03",
  "title": "第3節　帳簿等",
  "category": "shohi",
  "canonical_url": "https://www.nta.go.jp/law/tsutatsu/kihon/shohi/17/03.htm",
  "source_type": "tsutatsu",
  "crawled_at": "2026-04-12T06:01:29.949Z",
  "updated_at": null,
  "published_at": null,
  "content_hash": "sha256:4b8e014ec8768c82e145f4bdabd91d3fe0360e8e31ccf4af98110990d01a57d7",
  "license": "public_data",
  "version": 1,
  "aliases": [
    "第3節　帳簿等"
  ],
  "headings": [
    "第3節　帳簿等",
    "第3節　帳簿等",
    "（保存すべき帳簿）"
  ],
  "citation": null,
  "document_number": null,
  "tags": [
    "消費税"
  ],
  "etag": "\"e68-60f3503f6d7c0\"",
  "last_modified": "Thu, 18 Jan 2024 09:30:34 GMT"
}
