{
  "id": "1937",
  "title": "居住者が海外で株式等を売却した場合の課税関係等",
  "category": "shotoku",
  "category_path": "所得税（譲渡所得）",
  "canonical_url": "https://www.nta.go.jp/taxes/shiraberu/taxanswer/shotoku/1937.htm",
  "source_type": "tax_answer",
  "crawled_at": "2026-04-12T08:13:39.999Z",
  "updated_at": null,
  "published_at": null,
  "content_hash": "sha256:b9e1605b11df416e7ca15c8454c1a92e1970524fb6b1bc8dcbdb3f1dba3460c5",
  "license": "public_data",
  "version": 1,
  "aliases": [
    "No.1937 居住者が海外で株式等を売却した場合の課税関係等",
    "1937 居住者が海外で株式等を売却した場合の課税関係等"
  ],
  "headings": [
    "居住者が海外で株式等を売却した場合の課税関係等",
    "対象税目",
    "概要",
    "居住者の課税所得の範囲",
    "外国税額控除",
    "根拠法令等",
    "関連リンク",
    "関連コード",
    "お問い合わせ先"
  ],
  "etag": "\"3f6a-64a2398e5f8d8\"",
  "last_modified": "Fri, 06 Feb 2026 08:30:09 GMT"
}
