{
  "id": "2108",
  "title": "中古資産を非業務用から業務用に転用した場合の減価償却",
  "category": "shotoku",
  "category_path": "所得税",
  "canonical_url": "https://www.nta.go.jp/taxes/shiraberu/taxanswer/shotoku/2108.htm",
  "source_type": "tax_answer",
  "crawled_at": "2026-04-12T08:14:03.050Z",
  "updated_at": null,
  "published_at": null,
  "content_hash": "sha256:8823a2042d6d66c706937025c72b934be2aa6713cebafae2e3aeb54a78206fc0",
  "license": "public_data",
  "version": 1,
  "aliases": [
    "No.2108 中古資産を非業務用から業務用に転用した場合の減価償却",
    "2108 中古資産を非業務用から業務用に転用した場合の減価償却"
  ],
  "headings": [
    "中古資産を非業務用から業務用に転用した場合の減価償却",
    "対象税目",
    "概要",
    "計算方法・計算式",
    "業務の用に供した日における未償却残高相当額の計算",
    "業務の用に供した後の減価償却費の計算",
    "根拠法令等",
    "関連リンク",
    "関連コード",
    "QAリンク",
    "お問い合わせ先"
  ],
  "etag": "\"63da-6418ff5187348\"",
  "last_modified": "Mon, 20 Oct 2025 05:00:08 GMT"
}
