{
  "id": "tsutatsu-hojin-02-02_03_07a",
  "title": "第7款　ヘッジ処理による損益",
  "category": "hojin",
  "canonical_url": "https://www.nta.go.jp/law/tsutatsu/kihon/hojin/02/02_03_07a.htm",
  "source_type": "tsutatsu",
  "crawled_at": "2026-04-12T02:28:31.557Z",
  "updated_at": null,
  "published_at": null,
  "content_hash": "sha256:13b5606975e9a8486d016f70f966bcb74a9a5897dbcc37a41b2d3fc584b8b095",
  "license": "public_data",
  "version": 1,
  "aliases": [
    "第7款　ヘッジ処理による損益",
    "2-3-45"
  ],
  "headings": [
    "第7款　ヘッジ処理による損益",
    "第7款　ヘッジ処理による損益",
    "（繰延ヘッジ処理の対象となる取引の範囲）",
    "（ヘッジ手段の指定の単位）",
    "（売建オプション取引等の取扱い）",
    "（有効性判定の方法）",
    "（有効性判定の時期）",
    "（有効性判定の数値が異常値と認められる場合の取扱い）",
    "（ヘッジとして有効である部分の金額の特例）",
    "（ヘッジ期間の満了による繰延ヘッジ処理の終了）",
    "（キャッシュ・フローの変動に係る損失の範囲）",
    "（履行確定取引及び履行予定取引の意義）",
    "（予定取引が行われた場合の取扱い）",
    "（予定取引の中止が確実となった場合等の繰延ヘッジ処理の不適用）",
    "（包括ヘッジ処理の要件）",
    "（包括ヘッジ処理における決済損益額の配分）",
    "（繰延ヘッジ処理の表示）",
    "（繰延ヘッジ処理を適用している場合等における負債の利子の額の計算）",
    "（時価ヘッジ処理に係る取扱い）"
  ],
  "citation": null,
  "document_number": "2-3-45",
  "tags": [
    "法人税"
  ],
  "etag": "\"5b34-621fc07b0c748\"",
  "last_modified": "Fri, 13 Sep 2024 08:30:04 GMT"
}
