{
  "id": "3514",
  "title": "資産の一部を交換とし、一部を売買としたとき",
  "category": "joto",
  "category_path": "所得税（譲渡所得）",
  "canonical_url": "https://www.nta.go.jp/taxes/shiraberu/taxanswer/joto/3514.htm",
  "source_type": "tax_answer",
  "crawled_at": "2026-04-12T07:59:03.817Z",
  "updated_at": null,
  "published_at": null,
  "content_hash": "sha256:83520f4453d409dc99b4acbbf7f944b55242db40f52311d32d0d98c196e8e487",
  "license": "public_data",
  "version": 1,
  "aliases": [
    "No.3514 資産の一部を交換とし、一部を売買としたとき",
    "3514 資産の一部を交換とし、一部を売買としたとき"
  ],
  "headings": [
    "資産の一部を交換とし、一部を売買としたとき",
    "対象税目",
    "概要",
    "対象者または対象物",
    "根拠法令等",
    "関連リンク",
    "関連コード",
    "お問い合わせ先"
  ],
  "etag": "\"3719-641b4d730a4c0\"",
  "last_modified": "Wed, 22 Oct 2025 01:00:20 GMT"
}
