{
  "id": "1376",
  "title": "不動産所得の収入計上時期",
  "category": "shotoku",
  "category_path": "所得税",
  "canonical_url": "https://www.nta.go.jp/taxes/shiraberu/taxanswer/shotoku/1376.htm",
  "source_type": "tax_answer",
  "crawled_at": "2026-04-12T08:12:13.830Z",
  "updated_at": null,
  "published_at": null,
  "content_hash": "sha256:9ed4f4873b0361c8102287d765a15fc40e77eeb6c366ea3a87e10956a1f40db2",
  "license": "public_data",
  "version": 1,
  "aliases": [
    "No.1376 不動産所得の収入計上時期",
    "1376 不動産所得の収入計上時期"
  ],
  "headings": [
    "不動産所得の収入計上時期",
    "対象税目",
    "概要",
    "地代・家賃、共益費",
    "上記以外のもの",
    "根拠法令等",
    "QAリンク",
    "お問い合わせ先"
  ],
  "etag": "\"3929-641a0b92c54d8\"",
  "last_modified": "Tue, 21 Oct 2025 01:00:17 GMT"
}
