{
  "id": "qa-joto-19-08",
  "title": "買換資産を取得する予定であった者が、買換資産を全く取得しないまま死亡した場合の修正申告期限",
  "category": "joto",
  "category_path": "譲渡所得",
  "canonical_url": "https://www.nta.go.jp/law/shitsugi/joto/19/08.htm",
  "source_type": "qa_case",
  "crawled_at": "2026-04-12T05:51:48.978Z",
  "updated_at": null,
  "published_at": null,
  "content_hash": "sha256:86ee54b7c54bcd2ee6823de4545d90cd14b21c64face7e15aa777f687b28b415",
  "license": "国税庁 質疑応答事例（CC-BY 4.0 互換）",
  "version": 1,
  "aliases": [
    "買換資産を取得する予定であった者が、買換資産を全く取得しないまま死亡した場合の修正申告期限",
    "19-08"
  ],
  "headings": [
    "買換資産を取得する予定であった者が、買換資産を全く取得しないまま死亡した場合の修正申告期限",
    "買換資産を取得する予定であった者が、買換資産を全く取得しないまま死亡した場合の修正申告期限",
    "【照会要旨】",
    "【回答要旨】",
    "【関係法令通達】"
  ],
  "citation": "租税特別措置法第37条第1項・第4項、第37条の2第2項\n租税特別措置法関係通達37-24",
  "document_number": "19-08",
  "tags": [
    "譲渡所得"
  ],
  "etag": "\"1420-645080558a798\"",
  "last_modified": "Wed, 03 Dec 2025 08:30:12 GMT"
}
