{
  "id": "qa-hyoka-07-10",
  "title": "1株当たりの純資産価額D －寄附修正により利益積立金額が変動する場合の調整",
  "category": "hyoka",
  "category_path": "財産評価",
  "canonical_url": "https://www.nta.go.jp/law/shitsugi/hyoka/07/10.htm",
  "source_type": "qa_case",
  "crawled_at": "2026-04-12T05:51:21.948Z",
  "updated_at": null,
  "published_at": null,
  "content_hash": "sha256:d21f3c569354f4cbd698a5ed31616e107383c0509eae0b42b633a01bbf276507",
  "license": "国税庁 質疑応答事例（CC-BY 4.0 互換）",
  "version": 1,
  "aliases": [
    "1株当たりの純資産価額D －寄附修正により利益積立金額が変動する場合の調整",
    "07-10"
  ],
  "headings": [
    "1株当たりの純資産価額D －寄附修正により利益積立金額が変動する場合の調整",
    "1株当たりの純資産価額D －寄附修正により利益積立金額が変動する場合の調整",
    "【照会要旨】",
    "【回答要旨】",
    "【関係法令通達】"
  ],
  "citation": "財産評価基本通達183(3)\n法人税法施行令第9条第1項第7号",
  "document_number": "07-10",
  "tags": [
    "財産評価"
  ],
  "etag": "\"1770-64508060b7cd8\"",
  "last_modified": "Wed, 03 Dec 2025 08:30:23 GMT"
}
