{
  "id": "qa-gensen-03-06",
  "title": "海外の特定危険地域在住の従業員を被保険者とする損害保険契約の掛金を会社が負担する場合の経済的利益",
  "category": "gensen",
  "category_path": "源泉所得税",
  "canonical_url": "https://www.nta.go.jp/law/shitsugi/gensen/03/06.htm",
  "source_type": "qa_case",
  "crawled_at": "2026-04-12T05:50:51.082Z",
  "updated_at": null,
  "published_at": null,
  "content_hash": "sha256:982d5e0c170d89cc44eff68b04a5ab5975653a30b8505ae7cce8f44b28edc1fb",
  "license": "国税庁 質疑応答事例（CC-BY 4.0 互換）",
  "version": 1,
  "aliases": [
    "海外の特定危険地域在住の従業員を被保険者とする損害保険契約の掛金を会社が負担する場合の経済的利益",
    "03-06"
  ],
  "headings": [
    "海外の特定危険地域在住の従業員を被保険者とする損害保険契約の掛金を会社が負担する場合の経済的利益",
    "海外の特定危険地域在住の従業員を被保険者とする損害保険契約の掛金を会社が負担する場合の経済的利益",
    "【照会要旨】",
    "【回答要旨】",
    "【関係法令通達】"
  ],
  "citation": "所得税基本通達36-31の7",
  "document_number": "03-06",
  "tags": [
    "源泉所得税"
  ],
  "etag": "\"147b-6450809311f08\"",
  "last_modified": "Wed, 03 Dec 2025 08:31:16 GMT"
}
