{
  "id": "qa-shohi-20-14",
  "title": "一企業の特定の部門のみの簡易課税制度の適用",
  "category": "shohi",
  "category_path": "消費税",
  "canonical_url": "https://www.nta.go.jp/law/shitsugi/shohi/20/14.htm",
  "source_type": "qa_case",
  "crawled_at": "2026-04-12T05:52:01.909Z",
  "updated_at": null,
  "published_at": null,
  "content_hash": "sha256:81a5aea03d2a33b4586ad91d31035379dd2a60551c1c1503ae94645d0ac7e832",
  "license": "国税庁 質疑応答事例（CC-BY 4.0 互換）",
  "version": 1,
  "aliases": [
    "一企業の特定の部門のみの簡易課税制度の適用",
    "20-14"
  ],
  "headings": [
    "一企業の特定の部門のみの簡易課税制度の適用",
    "一企業の特定の部門のみの簡易課税制度の適用",
    "【照会要旨】",
    "【回答要旨】",
    "【関係法令通達】"
  ],
  "citation": "消費税法第37条第1項",
  "document_number": "20-14",
  "tags": [
    "消費税"
  ],
  "etag": "\"11ae-6450806b04c40\"",
  "last_modified": "Wed, 03 Dec 2025 08:30:34 GMT"
}
