{
  "id": "tsutatsu-chosyu-801028-01",
  "title": "滞納処分により差押えをした債権につき債権者不確知を理由として供託された場合に国が採るべき徴収手段について",
  "category": "chosyu",
  "canonical_url": "https://www.nta.go.jp/law/tsutatsu/kobetsu/chosyu/801028/01.htm",
  "source_type": "tsutatsu",
  "crawled_at": "2026-04-12T10:04:09.521Z",
  "updated_at": null,
  "published_at": null,
  "content_hash": "sha256:d5a20affc56eaeb4990ca6acd6576685a623062cc90666b510784f213a0009b2",
  "license": "public_data",
  "version": 1,
  "aliases": [
    "滞納処分により差押えをした債権につき債権者不確知を理由として供託された場合に国が採るべき徴収手段について"
  ],
  "headings": [
    "滞納処分により差押えをした債権につき債権者不確知を理由として供託された場合に国が採るべき徴収手段について",
    "滞納処分により差押えをした債権につき債権者不確知を理由として供託された場合に国が採るべき徴収手段について",
    "1　供託金の還付請求権について、滞納者が譲渡等の処分をしていないと認められるとき。",
    "2　供託金の還付請求権について滞納者が譲渡等の処分をしていると認められるとき。"
  ],
  "citation": null,
  "document_number": null,
  "tags": [
    "chosyu"
  ],
  "etag": "\"17e2-60f35010c6200\"",
  "last_modified": "Thu, 18 Jan 2024 09:29:45 GMT"
}
