{
  "id": "qa-hotei-8-03",
  "title": "同一年中に一の勤務先から、使用人としての退職金と役員退職金の双方の支給があった場合の記載方法",
  "category": "hotei",
  "category_path": "法定調書",
  "canonical_url": "https://www.nta.go.jp/law/shitsugi/hotei/8/03.htm",
  "source_type": "qa_case",
  "crawled_at": "2026-04-12T06:20:00.000Z",
  "updated_at": null,
  "published_at": null,
  "content_hash": "sha256:f187e674c14c4331fe9558d13a8ed78258417f56bb50274f9c2487eaf5fd87d5",
  "license": "国税庁 質疑応答事例（CC-BY 4.0 互換）",
  "version": 1,
  "aliases": [
    "同一年中に一の勤務先から、使用人としての退職金と役員退職金の双方の支給があった場合の記載方法",
    "8-03"
  ],
  "headings": [
    "同一年中に一の勤務先から、使用人としての退職金と役員退職金の双方の支給があった場合の記載方法",
    "同一年中に一の勤務先から、使用人としての退職金と役員退職金の双方の支給があった場合の記載方法",
    "【照会要旨】",
    "【回答要旨】",
    "【関係法令通達】"
  ],
  "citation": "所得税法第30条、第201条、所得税法施行令第69条、第69条の2、第71条の2、所得税法施行規則第94条、別表第六（二）",
  "document_number": "8-03",
  "tags": [
    "法定調書"
  ],
  "etag": "\"1941-64df9e8b655b8\"",
  "last_modified": "Fri, 27 Mar 2026 04:26:46 GMT"
}
