{
  "id": "1466",
  "title": "同一銘柄の株式等を2回以上にわたって購入している場合の取得費",
  "category": "shotoku",
  "category_path": "所得税（譲渡所得）",
  "canonical_url": "https://www.nta.go.jp/taxes/shiraberu/taxanswer/shotoku/1466.htm",
  "source_type": "tax_answer",
  "crawled_at": "2026-04-12T08:12:29.868Z",
  "updated_at": null,
  "published_at": null,
  "content_hash": "sha256:3c9a7e263dcb37d78e7d6e8c61c2466f4e6258d25027a1612dcb33e5a4baef21",
  "license": "public_data",
  "version": 1,
  "aliases": [
    "No.1466 同一銘柄の株式等を2回以上にわたって購入している場合の取得費",
    "1466 同一銘柄の株式等を2回以上にわたって購入している場合の取得費"
  ],
  "headings": [
    "同一銘柄の株式等を2回以上にわたって購入している場合の取得費",
    "対象税目",
    "概要",
    "譲渡した株式等の取得費の概要",
    "計算方法・計算式",
    "具体例",
    "根拠法令等",
    "関連リンク",
    "お問い合わせ先"
  ],
  "etag": "\"42d4-64a2398eba5f8\"",
  "last_modified": "Fri, 06 Feb 2026 08:30:10 GMT"
}
