{
  "id": "tsutatsu-hojin-15-15_01_12",
  "title": "第12款　印刷業",
  "category": "hojin",
  "canonical_url": "https://www.nta.go.jp/law/tsutatsu/kihon/hojin/15/15_01_12.htm",
  "source_type": "tsutatsu",
  "crawled_at": "2026-04-12T10:09:53.856Z",
  "updated_at": null,
  "published_at": null,
  "content_hash": "sha256:a95f5078742d61d32add5c022f6e6dbb6e8127704fc8e9dd3396aa9f60418076",
  "license": "public_data",
  "version": 1,
  "aliases": [
    "第12款　印刷業"
  ],
  "headings": [
    "第12款　印刷業",
    "第12款　印刷業",
    "（印刷業の範囲）"
  ],
  "citation": null,
  "document_number": null,
  "tags": [
    "法人税"
  ],
  "etag": "\"e6a-60f350804baf8\"",
  "last_modified": "Thu, 18 Jan 2024 09:31:42 GMT"
}
