{
  "id": "tsutatsu-chosyu-05-04-132-01",
  "title": "第132条関係　換価代金等の交付期日",
  "category": "chosyu",
  "canonical_url": "https://www.nta.go.jp/law/tsutatsu/kihon/chosyu/05/04/132/01.htm",
  "source_type": "tsutatsu",
  "crawled_at": "2026-04-12T10:02:09.402Z",
  "updated_at": null,
  "published_at": null,
  "content_hash": "sha256:0728d87e7eebe54f3130860a41827f68d95b6d442026aa70ee1c374007aa52d1",
  "license": "public_data",
  "version": 1,
  "aliases": [
    "第132条関係　換価代金等の交付期日"
  ],
  "headings": [
    "第132条関係　換価代金等の交付期日",
    "第132条関係　換価代金等の交付期日",
    "交付期日"
  ],
  "citation": null,
  "document_number": null,
  "tags": [
    "chosyu"
  ],
  "etag": "\"118a-60f35088bd8d0\"",
  "last_modified": "Thu, 18 Jan 2024 09:31:51 GMT"
}
