{
  "id": "tsutatsu-shotoku-shinkoku-500401-01",
  "title": "農業災害補償法に基く農業共済金の課税時期について",
  "category": "shotoku",
  "canonical_url": "https://www.nta.go.jp/law/tsutatsu/kobetsu/shotoku/shinkoku/500401/01.htm",
  "source_type": "tsutatsu",
  "crawled_at": "2026-04-12T10:43:02.674Z",
  "updated_at": null,
  "published_at": null,
  "content_hash": "sha256:4dc98271d50456007c62656b77743285e2441b9ad6026044ccfc26b04bab6edd",
  "license": "public_data",
  "version": 1,
  "aliases": [
    "農業災害補償法に基く農業共済金の課税時期について"
  ],
  "headings": [
    "農業災害補償法に基く農業共済金の課税時期について",
    "農業災害補償法に基く農業共済金の課税時期について"
  ],
  "citation": null,
  "document_number": null,
  "tags": [
    "所得税"
  ],
  "etag": "\"1380-60f34f0f58838\"",
  "last_modified": "Thu, 18 Jan 2024 09:25:15 GMT"
}
