{
  "id": "bunshokaito-hojin-120117",
  "title": "マンション管理組合が区分所有者以外の者へのマンション駐車場の使用を認めた場合の収益事業の判定について(照会)",
  "category": "hojin",
  "canonical_url": "https://www.nta.go.jp/law/bunshokaito/hojin/120117/index.htm",
  "source_type": "written_answer",
  "crawled_at": "2026-04-12T05:25:49.770Z",
  "updated_at": null,
  "published_at": null,
  "content_hash": "sha256:9df3f63c32fc0ac0f044f1aa4e04e3db8ccc7db685c16f1e909a904547cd3b33",
  "license": "国税庁 文書回答事例（利用規約に従って再配布）",
  "version": 1,
  "aliases": [],
  "headings": [
    "マンション管理組合が区分所有者以外の者へのマンション駐車場の使用を認めた場合の収益事業の判定について(照会)"
  ],
  "citation": "取引等に係る税務上の取扱い等に関する照会(同業者団体等用)",
  "document_number": "120117",
  "page_offsets": [],
  "etag": "\"1d8a-64df9ea10c150\"",
  "last_modified": "Fri, 27 Mar 2026 04:27:09 GMT"
}
