{
  "id": "qa-shotoku-02-37",
  "title": "「ふるさと納税」を支出した者が地方公共団体から謝礼を受けた場合の課税関係",
  "category": "shotoku",
  "category_path": "所得税",
  "canonical_url": "https://www.nta.go.jp/law/shitsugi/shotoku/02/37.htm",
  "source_type": "qa_case",
  "crawled_at": "2026-04-12T05:52:07.450Z",
  "updated_at": null,
  "published_at": null,
  "content_hash": "sha256:293301e2cde9997fb6f7896671b846137a3eec189a88ad14f1abb07579f0e13a",
  "license": "国税庁 質疑応答事例（CC-BY 4.0 互換）",
  "version": 1,
  "aliases": [
    "「ふるさと納税」を支出した者が地方公共団体から謝礼を受けた場合の課税関係",
    "02-37"
  ],
  "headings": [
    "「ふるさと納税」を支出した者が地方公共団体から謝礼を受けた場合の課税関係",
    "「ふるさと納税」を支出した者が地方公共団体から謝礼を受けた場合の課税関係",
    "【照会要旨】",
    "【回答要旨】",
    "【関係法令通達】"
  ],
  "citation": "所得税法第9条、第34条、第36条、所得税基本通達34-1(5)、地方自治法第2条第1項",
  "document_number": "02-37",
  "tags": [
    "所得税"
  ],
  "etag": "\"16e5-64508089705d0\"",
  "last_modified": "Wed, 03 Dec 2025 08:31:06 GMT"
}
