{
  "id": "saiketsu-05-018",
  "title": "（平成28年1月13日裁決）",
  "category": "納税の猶予と担保",
  "category_code": "05",
  "canonical_url": "https://www.kfs.go.jp/service/JP/102/01/index.html",
  "source_type": "saiketsu",
  "crawled_at": "2026-04-12T06:30:00.000Z",
  "updated_at": null,
  "published_at": "2016-01-13",
  "content_hash": "sha256:9e2f97a7e271748ac37cc400def5a55d49364e1b62303990bb69941fa2946cf6",
  "license": "国税不服審判所 公表裁決事例（利用規約に従って再配布）",
  "version": 1,
  "aliases": [
    "（平成28年1月13日裁決）",
    "102-01",
    "平成28年1月13日裁決"
  ],
  "headings": [
    "（平成28年1月13日裁決）",
    "1 事実",
    "(1) 事案の概要",
    "(2) 審査請求に至る経緯及び基礎事実",
    "(3) 関係法令の要旨",
    "(4) 争点",
    "2 主張",
    "(1) 請求人",
    "(2) 原処分庁",
    "3 判断",
    "(1) 法令解釈等",
    "(2) 当てはめ",
    "(3) 請求人の主張について",
    "(4) 本件不許可処分の適法性について",
    "(5) その他"
  ],
  "citation": "平成28年1月13日裁決",
  "document_number": "102-01",
  "tags": [
    "納税の猶予と担保",
    "国税通則法"
  ],
  "etag": "\"58bc-64e399eea0070\"",
  "last_modified": "Mon, 30 Mar 2026 08:27:26 GMT"
}
