{
  "id": "tsutatsu-hojin-09-09_05_05",
  "title": "第５款　簿外経費",
  "category": "hojin",
  "canonical_url": "https://www.nta.go.jp/law/tsutatsu/kihon/hojin/09/09_05_05.htm",
  "source_type": "tsutatsu",
  "crawled_at": "2026-04-12T02:30:57.672Z",
  "updated_at": null,
  "published_at": null,
  "content_hash": "sha256:7401a59befafd89eee2c01425ef20b935b10900cac44467b722ccbbbe44ce283",
  "license": "public_data",
  "version": 1,
  "aliases": [
    "第５款　簿外経費",
    "9-5-8"
  ],
  "headings": [
    "第５款　簿外経費",
    "第５款　簿外経費",
    "（災害その他やむを得ない事情の範囲）",
    "（帳簿書類その他の物件の意義）",
    "（取引が行われたことが推測される場合）",
    "（相手方に対する調査その他の方法）"
  ],
  "citation": null,
  "document_number": "9-5-8",
  "tags": [
    "法人税"
  ],
  "etag": "\"19be-64a2398b47510\"",
  "last_modified": "Fri, 06 Feb 2026 08:30:06 GMT"
}
