{
  "id": "5501",
  "title": "一括評価金銭債権に係る貸倒引当金の設定",
  "category": "hojin",
  "category_path": "法人税",
  "canonical_url": "https://www.nta.go.jp/taxes/shiraberu/taxanswer/hojin/5501.htm",
  "source_type": "tax_answer",
  "crawled_at": "2026-04-12T06:09:41.663Z",
  "updated_at": null,
  "published_at": null,
  "content_hash": "sha256:b71127d9fd40534c527b57204354202a549fbab69aedd0c990d420bc54bd3309",
  "license": "public_data",
  "version": 1,
  "aliases": [
    "No.5501 一括評価金銭債権に係る貸倒引当金の設定",
    "5501 一括評価金銭債権に係る貸倒引当金の設定"
  ],
  "headings": [
    "一括評価金銭債権に係る貸倒引当金の設定",
    "対象税目",
    "概要",
    "実績繰入率に基づく計算（原則）",
    "法定繰入率に基づく計算（中小法人または公益法人等もしくは協同組合等向けの特例）",
    "根拠法令等",
    "関連コード",
    "お問い合わせ先"
  ],
  "etag": "\"4d5e-641bb1f873788\"",
  "last_modified": "Wed, 22 Oct 2025 08:30:03 GMT"
}
