{
  "id": "9205",
  "title": "延滞税について",
  "category": "osirase",
  "category_path": null,
  "canonical_url": "https://www.nta.go.jp/taxes/shiraberu/taxanswer/osirase/9205.htm",
  "source_type": "tax_answer",
  "crawled_at": "2026-04-12T07:59:12.847Z",
  "updated_at": null,
  "published_at": null,
  "content_hash": "sha256:a4da97de05f5dd307993cdac6b9ea294a5bef3bb944cfa2813f5d0cfc98321d4",
  "license": "public_data",
  "version": 1,
  "aliases": [
    "No.9205 延滞税について",
    "9205 延滞税について"
  ],
  "headings": [
    "延滞税について",
    "概要",
    "延滞税がかかる場合",
    "延滞税の割合",
    "令和3年1月1日以後の割合",
    "令和2年12月31日以前の割合",
    "延滞税の計算期間の特例",
    "根拠法令等",
    "関連リンク",
    "お問い合わせ先"
  ],
  "etag": "\"4a84-644a36f807ed0\"",
  "last_modified": "Fri, 28 Nov 2025 08:30:01 GMT"
}
